medialaxis3d/__init__.py
medialaxis3d/skeletonize_cy.c
medialaxis3d/skeletonize_cy.cpython-313-x86_64-linux-gnu.so
medialaxis3d/skeletonize_cy.pyx
medialaxis3d/luts/luts.npz
medialaxis3d-1.0.3.dist-info/METADATA
medialaxis3d-1.0.3.dist-info/WHEEL
medialaxis3d-1.0.3.dist-info/top_level.txt
medialaxis3d-1.0.3.dist-info/RECORD
