Metadata-Version: 2.4
Name: medialaxis3d
Version: 1.0.3
Summary: Module to perform 3D skeletonization using Medial Axis Transform
Author-email: Giovanni Bocchi <giovanni.bocchi1@unimi.it>
Maintainer-email: Giovanni Bocchi <giovanni.bocchi1@unimi.it>
License-Expression: MIT
Project-URL: Homepage, https://github.com/jb-sharp/medialaxis3d
Project-URL: Bug Reports, https://github.com/jb-sharp/medialaxis3d/issues
Project-URL: Source, https://github.com/jb-sharp/medialaxis3d
Keywords: MAT,skeletonization,3D
Classifier: Development Status :: 4 - Beta
Classifier: Intended Audience :: Science/Research
Classifier: Topic :: Scientific/Engineering :: Image Processing
Classifier: Programming Language :: Python :: 3
Classifier: Programming Language :: Python :: 3.8
Classifier: Programming Language :: Python :: 3.9
Classifier: Programming Language :: Python :: 3.10
Classifier: Programming Language :: Python :: 3.11
Classifier: Programming Language :: Python :: 3.12
Classifier: Programming Language :: Python :: 3.13
Classifier: Programming Language :: Python :: 3 :: Only
Classifier: Operating System :: OS Independent
Requires-Python: >=3.8
Requires-Dist: scipy>=1.15.2
Requires-Dist: numpy>=2.1.3
Requires-Dist: cython>=3.0.11
Provides-Extra: visualization
Requires-Dist: napari>=0.5.6; extra == "visualization"
